spectromancer/__init__.py
spectromancer/__main__.py
spectromancer/spectromancer.py
spectromancer-0.1.8.dist-info/METADATA
spectromancer-0.1.8.dist-info/WHEEL
spectromancer-0.1.8.dist-info/entry_points.txt
spectromancer-0.1.8.dist-info/top_level.txt
spectromancer-0.1.8.dist-info/RECORD
