Metadata-Version: 2.1
Name: spectromancer
Version: 0.1.8
Summary: spectromancer.py is a wizard for managing MAGE spectrum observations of white dwarfs
Author-email: Stefan Arseneau <arseneau@bu.edu>
Project-URL: Homepage, https://github.com/stefanarseneau/spectromancer.py
Project-URL: Issues, https://github.com/stefanarseneau/spectromancer.py/issues
Classifier: Programming Language :: Python :: 3
Classifier: License :: OSI Approved :: MIT License
Classifier: Operating System :: OS Independent
Requires-Python: >=3.8
